pyHappyOrNot/__init__.py
pyHappyOrNot/pyHappyOrNot.py
pyHappyOrNot-0.0.3.dist-info/DESCRIPTION.rst
pyHappyOrNot-0.0.3.dist-info/METADATA
pyHappyOrNot-0.0.3.dist-info/metadata.json
pyHappyOrNot-0.0.3.dist-info/pbr.json
pyHappyOrNot-0.0.3.dist-info/RECORD
pyHappyOrNot-0.0.3.dist-info/top_level.txt
pyHappyOrNot-0.0.3.dist-info/WHEEL
