Metadata-Version: 2.0
Name: pyHappyOrNot
Version: 0.0.3
Summary: A wrapper around the HappyOrNot API
Home-page: https://github.com/18f/pyHappyOrNot
Author: V. David Zvenyach
Author-email: vladlen.zvenyach@gsa.gov
License: CC0
Keywords: HappyOrNot
Platform: UNKNOWN
Classifier: Development Status :: 3 - Alpha
Classifier: Programming Language :: Python :: 3.4
Requires-Dist: requests
